bigonavigator/__init__.py
bigonavigator/example.py
BigONavigator-0.2.2.dist-info/METADATA
BigONavigator-0.2.2.dist-info/WHEEL
BigONavigator-0.2.2.dist-info/top_level.txt
BigONavigator-0.2.2.dist-info/RECORD
