Metadata-Version: 2.1
Name: BigONavigator
Version: 0.2.2
Summary: A Python package to track and document the computational complexity of functions.
Author-email: Daniel Rosel <daniel@alves.world>
Project-URL: Homepage, https://github.com/velocitatem/bigOnavigator
Project-URL: Documentation, https://velocitatem.github.io/bigOnavigator
Project-URL: Source, https://github.com/velocitatem/bigOnavigator
Project-URL: Issues, https://github.com/velocitatem/bigOnavigator/issues
Classifier: Programming Language :: Python :: 3
Classifier: License :: OSI Approved :: MIT License
Classifier: Operating System :: OS Independent
Requires-Python: >=3.8
